llama_index/tools/agentql/__init__.py
llama_index/tools/agentql/const.py
llama_index/tools/agentql/messages.py
llama_index/tools/agentql/utils.py
llama_index/tools/agentql/agentql_browser_tool/__init__.py
llama_index/tools/agentql/agentql_browser_tool/base.py
llama_index/tools/agentql/agentql_rest_api_tool/__init__.py
llama_index/tools/agentql/agentql_rest_api_tool/base.py
llama_index_tools_agentql-1.2.0.dist-info/METADATA
llama_index_tools_agentql-1.2.0.dist-info/WHEEL
llama_index_tools_agentql-1.2.0.dist-info/RECORD
