Metadata-Version: 2.4
Name: llama-index-tools-agentql
Version: 1.2.0
Summary: llama-index tools agentql integration
Author-email: Jason Zhang <jason@tinyfish.io>
Maintainer-email: Jason Zhang <jason@tinyfish.io>
License-Expression: MIT
Requires-Python: <4.0,>=3.9
Requires-Dist: agentql<2,>=1.8.1
Requires-Dist: httpx<0.29,>=0.28.1
Requires-Dist: llama-index-core<0.15,>=0.10.0
Requires-Dist: playwright<2,>=1.50.0
